fetch_my_weather/__init__.py
fetch_my_weather/core.py
fetch_my_weather/models.py
fetch_my_weather-0.3.0.dist-info/licenses/AUTHORS.md
fetch_my_weather-0.3.0.dist-info/licenses/LICENSE
fetch_my_weather-0.3.0.dist-info/METADATA
fetch_my_weather-0.3.0.dist-info/WHEEL
fetch_my_weather-0.3.0.dist-info/top_level.txt
fetch_my_weather-0.3.0.dist-info/RECORD
