Metadata-Version: 2.4
Name: fetch-my-weather
Version: 0.3.0
Summary: A beginner-friendly Python package for fetching weather data, designed for educational use.
Author-email: Your Name <your.email@example.com>
License: MIT
Project-URL: Homepage, https://github.com/michael-borck/fetch-my-weather
Project-URL: Documentation, https://michaelborck.au/fetch-my-weather/
Project-URL: Issues, https://github.com/michael-borck/fetch-my-weather/issues
Classifier: Programming Language :: Python :: 3
Classifier: Programming Language :: Python :: 3.10
Classifier: Programming Language :: Python :: 3.11
Classifier: License :: OSI Approved :: MIT License
Classifier: Operating System :: OS Independent
Classifier: Intended Audience :: Education
Classifier: Topic :: Education
Classifier: Topic :: Scientific/Engineering :: Atmospheric Science
Requires-Python: >=3.10
License-File: LICENSE
License-File: AUTHORS.md
Requires-Dist: requests>=2.25.0
Requires-Dist: pydantic>=1.8.0
Provides-Extra: dev
Requires-Dist: pytest>=7.0.0; extra == "dev"
Requires-Dist: pytest-mock>=3.10.0; extra == "dev"
Requires-Dist: ruff>=0.1.6; extra == "dev"
Requires-Dist: mypy>=1.5.0; extra == "dev"
Requires-Dist: twine==6.0.1; extra == "dev"
Dynamic: license-file
